sort_contigs/__init__.py
sort_contigs/__init__.py~
sort_contigs-0.2.2.dist-info/WHEEL
sort_contigs-0.2.2.dist-info/entry_points.txt
sort_contigs-0.2.2.dist-info/METADATA
sort_contigs-0.2.2.dist-info/RECORD
