Metadata-Version: 2.4
Name: sort-contigs
Version: 0.2.2
Summary: Add your description here
Author: Paul Grablowitz
Author-email: Paul Grablowitz <paul.grablowitz@student.uni-tuebingen.de>
License-Expression: MIT
Requires-Dist: biopython>=1.85
Requires-Dist: numpy>=2.0.2
Requires-Dist: pandas>=2.3.3
Requires-Python: >=3.9
